timezonemapper/__init__.py
timezonemapper/mapper.py
timezonemapper-0.1.dist-info/METADATA
timezonemapper-0.1.dist-info/WHEEL
timezonemapper-0.1.dist-info/top_level.txt
timezonemapper-0.1.dist-info/RECORD
